setup.py
LogCollectionFormatter/__init__.py
LogCollectionFormatter/base_log.py
LogCollectionFormatter/insert_mq_tools.py
LogCollectionFormatter/main_log.py
LogCollectionFormatter.egg-info/PKG-INFO
LogCollectionFormatter.egg-info/SOURCES.txt
LogCollectionFormatter.egg-info/dependency_links.txt
LogCollectionFormatter.egg-info/top_level.txt