Metadata-Version: 1.1
Name: LogCollectionFormatter
Version: 1.2.0
Summary: A python log handler format log messages and records them by loggin module
Home-page: UNKNOWN
Author: Licong
Author-email: 17601072928@sina.cn
License: MIT
Keywords: log collection formatter includes debug,info,error,warn,external,internal functions to formats and records log message
Platform: all
Classifier: Development Status :: 3 - Alpha
Classifier: Intended Audience :: Developers
Classifier: Topic :: Software Development :: Libraries
Classifier: License :: OSI Approved :: MIT License
Classifier: Programming Language :: Python :: 2.7
Classifier: Programming Language :: Python :: 3.5
Classifier: Programming Language :: Python :: 3.6
Classifier: Programming Language :: Python :: 3.7
